lib2to3import.py
lib2to3import-2020.11.17.post1.dist-info/LICENSE
lib2to3import-2020.11.17.post1.dist-info/METADATA
lib2to3import-2020.11.17.post1.dist-info/WHEEL
lib2to3import-2020.11.17.post1.dist-info/top_level.txt
lib2to3import-2020.11.17.post1.dist-info/RECORD
