Metadata-Version: 2.1
Name: lib2to3import
Version: 2020.11.17.post1
Summary: lib2to3import is a utility to apply Python 2 to 3 code translation on import.
Home-page: https://github.com/sakurai-youhei/lib2to3import
Author: Youhei Sakurai
Author-email: sakurai.youhei@gmail.com
License: MIT
Keywords: 2to3,lib2to3,import,importer
Platform: UNKNOWN
Classifier: License :: OSI Approved :: MIT License
Classifier: Development Status :: 3 - Alpha
Classifier: Programming Language :: Python :: 3.4
Classifier: Programming Language :: Python :: 3.5
Classifier: Programming Language :: Python :: 3.6
Classifier: Intended Audience :: Developers
Requires-Dist: chardet
